LICENSE.txt
MANIFEST.in
README.md
requirements.txt
setup.py
src/automated_ml_pack/__init__.py
src/automated_ml_pack/train_pipeline.py
src/automated_ml_pack.egg-info/PKG-INFO
src/automated_ml_pack.egg-info/SOURCES.txt
src/automated_ml_pack.egg-info/dependency_links.txt
src/automated_ml_pack.egg-info/entry_points.txt
src/automated_ml_pack.egg-info/requires.txt
src/automated_ml_pack.egg-info/top_level.txt
src/automated_ml_pack/modules/__init__.py
src/automated_ml_pack/modules/exception.py
src/automated_ml_pack/modules/logger.py
src/automated_ml_pack/modules/params.py
src/automated_ml_pack/modules/run_train_pipeline.py
src/automated_ml_pack/modules/utils.py
src/automated_ml_pack/modules/components/__init__.py
src/automated_ml_pack/modules/components/data_ingestion.py
src/automated_ml_pack/modules/components/data_transformation.py
src/automated_ml_pack/modules/components/model_trainer.py